summer/__init__.py
summer/adjust.py
summer/compartment.py
summer/compute.py
summer/derived_outputs.py
summer/flows.py
summer/inspect.py
summer/model.py
summer/population.py
summer/runner/__init__.py
summer/runner/model_runner.py
summer/runner/reference_runner.py
summer/runner/vectorized_runner.py
summer/solver.py
summer/stochastic.py
summer/stratification.py
summer/utils.py
summerepi-3.6.4.dist-info/LICENSE.txt
summerepi-3.6.4.dist-info/METADATA
summerepi-3.6.4.dist-info/WHEEL
summerepi-3.6.4.dist-info/RECORD
