Metadata-Version: 2.1
Name: summerepi
Version: 3.6.4
Summary: Summer is a compartmental disease modelling framework, written in Python. It provides a high-level API to build and run models.
Home-page: http://summerepi.com/
License: BSD-2-Clause
Keywords: epidemiology,disease,compartmental,infectious
Author: James Trauer
Author-email: james.trauer@monash.edu
Requires-Python: >=3.7.1,<3.11
Classifier: License :: OSI Approved :: BSD License
Classifier: Programming Language :: Python :: 3
Classifier: Programming Language :: Python :: 3.8
Classifier: Programming Language :: Python :: 3.9
Classifier: Programming Language :: Python :: 3.10
Provides-Extra: docs
Requires-Dist: ipykernel (>=6.15.1,<7.0.0) ; extra == "docs"
Requires-Dist: matplotlib (>=3.4.3) ; extra == "docs"
Requires-Dist: nbsphinx (>=0.8.2,<0.9.0) ; extra == "docs"
Requires-Dist: networkx (>=2.6.2)
Requires-Dist: numba (>=0.54.0)
Requires-Dist: numpy (>=1.20.3)
Requires-Dist: pandas (>=1.3.2)
Requires-Dist: recommonmark (>=0.7.1,<0.8.0) ; extra == "docs"
Requires-Dist: scipy (>=1.7.1)
Requires-Dist: setuptools (>=59.8.0)
Requires-Dist: sphinx-rtd-theme (>=0.5.1,<0.6.0) ; extra == "docs"
Requires-Dist: sphinxcontrib-napoleon (>=0.7,<0.8) ; extra == "docs"
Project-URL: Documentation, http://summerepi.com/
Project-URL: Repository, https://github.com/monash-emu/summer
